cmprs/__init__.py
cmprs/clipping.py
cmprs/common.py
cmprs/config.py
cmprs/kashin.py
cmprs/random_utils.py
cmprs/reshape.py
cmprs/rounding.py
cmprs/scale.py
cmprs/sparsification.py
cmprs/split.py
cmprs/transform.py
cmprs/bitrate/__init__.py
cmprs/bitrate/huffman_coding.py
cmprs/bitrate/optimal.py
cmprs/bitrate/recursive_elias_coding.py
cmprs/eden/__init__.py
cmprs/eden/drive.py
cmprs/eden/linear.py
distributed_mean_estimation-0.1a2.dist-info/LICENSE
distributed_mean_estimation-0.1a2.dist-info/METADATA
distributed_mean_estimation-0.1a2.dist-info/WHEEL
distributed_mean_estimation-0.1a2.dist-info/top_level.txt
distributed_mean_estimation-0.1a2.dist-info/RECORD
