Metadata-Version: 2.1
Name: distributed-mean-estimation
Version: 0.1a2
Summary: Algorithms for Distributed Mean Estimation (DME) in PyTorch
Home-page: https://github.com/amitport/distributed-mean-estimation
Author: Amit Portnoy
Author-email: amit.portnoy@gmail.com
Project-URL: Bug Tracker, https://github.com/amitport/distributed-mean-estimation/issues
Classifier: Programming Language :: Python :: 3
Classifier: License :: OSI Approved :: MIT License
Classifier: Operating System :: OS Independent
Requires-Python: >=3.9
License-File: LICENSE
Requires-Dist: torch (>=1.10)
Requires-Dist: hadamard-transform (==0.1.*)
Provides-Extra: preprocess
Requires-Dist: sympy (==1.10.*) ; extra == 'preprocess'
Requires-Dist: tqdm (==4.*) ; extra == 'preprocess'
Provides-Extra: test
Requires-Dist: pytest ; extra == 'test'
